examples/__init__.py
examples/greeter.py
examples/say_hello_script.py
func_to_script/__init__.py
func_to_script/_version.py
func_to_script/config_loader.py
func_to_script/core.py
func_to_script-1.1.0.dist-info/licenses/LICENSE.txt
test/scripts/__init__.py
test/scripts/script_no_defaults.py
test/scripts/script_with_defaults.py
test/scripts/script_with_incorrect_type.py
test/scripts/script_with_missing_types.py
func_to_script-1.1.0.dist-info/METADATA
func_to_script-1.1.0.dist-info/WHEEL
func_to_script-1.1.0.dist-info/top_level.txt
func_to_script-1.1.0.dist-info/RECORD
