Metadata-Version: 2.4
Name: func-to-script
Version: 1.1.0
Summary: func-to-script` is a lightweight and convenient tool which can be used to turn a Python function into a command line
Home-page: https://github.com/Chris-hughes10/func-to-script
Author: Chris Hughes
Author-email: 31883449+Chris-hughes10@users.noreply.github.com
Classifier: License :: OSI Approved :: MIT License
Classifier: Programming Language :: Python
Classifier: Programming Language :: Python :: 3
Classifier: Programming Language :: Python :: 3.7
Classifier: Programming Language :: Python :: 3.8
Classifier: Programming Language :: Python :: 3.9
Classifier: Programming Language :: Python :: 3.10
Classifier: Programming Language :: Python :: 3.11
Classifier: Programming Language :: Python :: 3.12
Classifier: Programming Language :: Python :: Implementation :: CPython
Requires-Python: >=3.8.0
License-File: LICENSE.txt
Requires-Dist: PyYAML>=5.1
Dynamic: author
Dynamic: author-email
Dynamic: classifier
Dynamic: description
Dynamic: description-content-type
Dynamic: home-page
Dynamic: license-file
Dynamic: requires-dist
Dynamic: requires-python
Dynamic: summary
